humbug_forensics.py
setup.py
humbug_forensics.egg-info/PKG-INFO
humbug_forensics.egg-info/SOURCES.txt
humbug_forensics.egg-info/dependency_links.txt
humbug_forensics.egg-info/requires.txt
humbug_forensics.egg-info/top_level.txt
humbug_forensics.egg-info/zip-safe
scripts/humbugger