Metadata-Version: 1.0
Name: humbug-forensics
Version: 0.0.0
Summary: Simple utility to fake "hum forensics"
Home-page: https://github.com/adamdeprince/humbug_forensics
Author: Adam DePrince
Author-email: deprince@googlealumni.com
License: UNKNOWN
Platform: UNKNOWN
